atcodercli/__builtins__.pyi
atcodercli/__init__.py
atcodercli/__main__.py
atcodercli/commands/__init__.py
atcodercli/commands/add_problem.py
atcodercli/commands/init_contest.py
atcodercli/commands/init_problem.py
atcodercli/commands/init_template.py
atcodercli/commands/login.py
atcodercli/commands/me.py
atcodercli/commands/submit_problem.py
atcodercli/commands/test_template.py
atcodercli/commands/watch_page.py
atcodercli/commands/watch_result.py
atcodercli/locales/zh_CN/LC_MESSAGES/atcodercli.mo
atcodercli/utils/__init__.py
atcodercli/utils/config.py
atcodercli/utils/confirm.py
atcodercli/utils/get_session.py
atcodercli/utils/problems.py
atcodercli-0.5.5.dist-info/METADATA
atcodercli-0.5.5.dist-info/WHEEL
atcodercli-0.5.5.dist-info/RECORD
